HISTORY.rst
README.rst
django_session_header/__init__.py
django_session_header/authentication.py
django_session_header/middleware.py
tests/conftest.py
tests/test_authentication.py
tests/test_middleware.py
django_session_header-1.0.dist-info/LICENSE
django_session_header-1.0.dist-info/WHEEL
django_session_header-1.0.dist-info/METADATA
django_session_header-1.0.dist-info/RECORD
